pyhomogenize/__init__.py
pyhomogenize/_basics.py
pyhomogenize/_consts.py
pyhomogenize/_netcdf_basics.py
pyhomogenize/_read_write.py
pyhomogenize/_time_compare.py
pyhomogenize/_time_control.py
pyhomogenize/_utilities.py
pyhomogenize/cli.py
pyhomogenize/data.py
pyhomogenize/pyhomogenize.py
pyhomogenize/data/netcdf/tas_EUR-11_MIROC-MIROC5_rcp85_r1i1p1_CLMcom-CCLM4-8-17_v1_mon_200701-200707.nc
pyhomogenize/data/netcdf/tas_EUR-11_MIROC-MIROC5_rcp85_r1i1p1_CLMcom-CCLM4-8-17_v1_mon_200701-200712.nc
pyhomogenize/data/netcdf/tas_EUR-11_MIROC-MIROC5_rcp85_r1i1p1_CLMcom-CCLM4-8-17_v1_mon_200705-200712.nc
pyhomogenize/data/netcdf/tas_EUR-11_MIROC-MIROC5_rcp85_r1i1p1_CLMcom-CCLM4-8-17_v1_mon_200801-200812.nc
pyhomogenize/operators/__init__.py
pyhomogenize/operators/merge.py
pyhomogenize/operators/seltimerange.py
pyhomogenize/operators/showdups.py
pyhomogenize/operators/showmiss.py
pyhomogenize/operators/showreds.py
pyhomogenize/operators/showtimestamps.py
pyhomogenize/operators/showvar.py
pyhomogenize/operators/timecheck.py
pyhomogenize-0.6.1.dist-info/AUTHORS.rst
pyhomogenize-0.6.1.dist-info/LICENSE
pyhomogenize-0.6.1.dist-info/METADATA
pyhomogenize-0.6.1.dist-info/WHEEL
pyhomogenize-0.6.1.dist-info/entry_points.txt
pyhomogenize-0.6.1.dist-info/top_level.txt
pyhomogenize-0.6.1.dist-info/RECORD
