Metadata-Version: 2.1
Name: pyhomogenize
Version: 0.6.1
Summary: Tool to homogenize netCDF files to CF standard
Home-page: https://github.com/ludwiglierhammer/pyhomogenize
Author: Ludwig Lierhammer
Author-email: ludwig.lierhammer@hereon.de
License: MIT license
Keywords: pyhomogenize
Classifier: Development Status :: 2 - Pre-Alpha
Classifier: Intended Audience :: Developers
Classifier: License :: OSI Approved :: MIT License
Classifier: Natural Language :: English
Classifier: Programming Language :: Python :: 3
Classifier: Programming Language :: Python :: 3.9
Classifier: Programming Language :: Python :: 3.10
Classifier: Programming Language :: Python :: 3.11
Requires-Python: >=3.9
License-File: LICENSE
License-File: AUTHORS.rst
Requires-Dist: dask (>=2021.9.1)
Requires-Dist: xarray (>=0.19.0)
Requires-Dist: iteration-utilities (>=0.11.0)
Requires-Dist: cftime
Requires-Dist: netcdf4
Requires-Dist: h5netcdf
